odoo/addons/account_move_line_partner_country/README.rst
odoo/addons/account_move_line_partner_country/__init__.py
odoo/addons/account_move_line_partner_country/__manifest__.py
odoo/addons/account_move_line_partner_country/i18n/account_move_line_partner_country.pot
odoo/addons/account_move_line_partner_country/models/__init__.py
odoo/addons/account_move_line_partner_country/models/account_move_line.py
odoo/addons/account_move_line_partner_country/readme/CONTRIBUTORS.rst
odoo/addons/account_move_line_partner_country/readme/DESCRIPTION.rst
odoo/addons/account_move_line_partner_country/static/description/icon.png
odoo/addons/account_move_line_partner_country/static/description/index.html
odoo/addons/account_move_line_partner_country/tests/__init__.py
odoo/addons/account_move_line_partner_country/views/account_move_line.xml
odoo12_addon_account_move_line_partner_country-12.0.1.0.0.99.dev4.dist-info/METADATA
odoo12_addon_account_move_line_partner_country-12.0.1.0.0.99.dev4.dist-info/WHEEL
odoo12_addon_account_move_line_partner_country-12.0.1.0.0.99.dev4.dist-info/top_level.txt
odoo12_addon_account_move_line_partner_country-12.0.1.0.0.99.dev4.dist-info/RECORD
